django_system_globals-0.0.8.dist-info/METADATA
django_system_globals-0.0.8.dist-info/RECORD
django_system_globals-0.0.8.dist-info/WHEEL
django_system_globals-0.0.8.dist-info/top_level.txt
system_globals/__init__.py
system_globals/admin.py
system_globals/context_processors.py
system_globals/models.py
system_globals/tests.py
system_globals/views.py
system_globals/migrations/0001_initial.py
system_globals/migrations/__init__.py
