Metadata-Version: 2.1
Name: django-system-globals
Version: 0.0.8
Summary: A Django App to manage any system globals from a DB table.
Home-page: https://github.com/andres-torres-marroquin/django-system-globals
Author: Andres Torres Marroquin
Author-email: andres.torres.marroquin@gmail.com
License: UNKNOWN
Platform: UNKNOWN
